setup.cfg
setup.py
turboentity.py
TurboEntity.egg-info/PKG-INFO
TurboEntity.egg-info/SOURCES.txt
TurboEntity.egg-info/dependency_links.txt
TurboEntity.egg-info/requires.txt
TurboEntity.egg-info/top_level.txt
TurboEntity.egg-info/zip-safe
