Metadata-Version: 1.0
Name: TurboEntity
Version: 0.1.0
Summary: Declarative layer on top of SQLAlchemy
Home-page: http://turboentity.ematia.de
Author: Daniel Haus
Author-email: daniel.haus@ematia.de
License: MIT
Download-URL: http://turboentity.ematia.de/
Keywords: sqlalchemy declarative database
Platform: UNKNOWN
Classifier: Development Status :: 3 - Alpha
Classifier: Framework :: TurboGears
Classifier: Intended Audience :: Developers
Classifier: License :: OSI Approved :: MIT License
Classifier: Operating System :: OS Independent
Classifier: Programming Language :: Python
Classifier: Topic :: Database :: Front-Ends
Classifier: Topic :: Software Development :: Libraries :: Python Modules
